rbac/__init__.py
rbac/decorators.py
rbac/permissions.py
rbac/utils.py
rbac_library-0.1.0.dist-info/METADATA
rbac_library-0.1.0.dist-info/WHEEL
rbac_library-0.1.0.dist-info/top_level.txt
rbac_library-0.1.0.dist-info/RECORD
