Metadata-Version: 2.1
Name: rbac-library
Version: 0.1.0
Summary: Role-Based Access Control Library for Django
Author: Sravan
Author-email: your.email@example.com
Classifier: Programming Language :: Python :: 3
Classifier: Framework :: Django
Classifier: License :: OSI Approved :: MIT License
Classifier: Operating System :: OS Independent
Requires-Dist: django >=3.2
